pytorch_adaptive_computation_time/__init__.py
pytorch_adaptive_computation_time/models.py
pytorch_adaptive_computation_time/tasks/addition.py
pytorch_adaptive_computation_time/tasks/parity.py
pytorch_adaptive_computation_time-0.1.3.dist-info/entry_points.txt
pytorch_adaptive_computation_time-0.1.3.dist-info/LICENSE
pytorch_adaptive_computation_time-0.1.3.dist-info/WHEEL
pytorch_adaptive_computation_time-0.1.3.dist-info/METADATA
pytorch_adaptive_computation_time-0.1.3.dist-info/RECORD
