Metadata-Version: 2.1
Name: pytorch-adaptive-computation-time
Version: 0.1.3
Summary: Implements adaptive computation time RNNs in PyTorch, with the same interface as builtin RNNs.
Home-page: https://github.com/maxwells-daemons/pytorch-adaptive-computation-time
License: Apache-2.0
Keywords: pytorch,adaptive-computation-time,rnn,machine-learning,neural-network
Author: maxwells-daemons
Author-email: aidanswope@gmail.com
Requires-Python: >=3.6.10,<4.0.0
Classifier: Environment :: GPU
Classifier: Environment :: GPU :: NVIDIA CUDA
Classifier: Intended Audience :: Developers
Classifier: Intended Audience :: Science/Research
Classifier: License :: OSI Approved :: Apache Software License
Classifier: Natural Language :: English
Classifier: Programming Language :: Python :: 3
Classifier: Programming Language :: Python :: 3.7
Classifier: Programming Language :: Python :: 3.8
Classifier: Topic :: Scientific/Engineering
Classifier: Topic :: Scientific/Engineering :: Artificial Intelligence
Classifier: Topic :: Software Development :: Libraries
Classifier: Topic :: Software Development :: Libraries :: Python Modules
Classifier: Typing :: Typed
Provides-Extra: docs
Requires-Dist: pytorch-lightning (==0.8.5)
Requires-Dist: sphinx (>=3.2.0,<4.0.0); extra == "docs"
Requires-Dist: sphinx-argparse (>=0.2.5,<0.3.0); extra == "docs"
Requires-Dist: torch (>=1.5.0,<2.0.0)
Project-URL: Documentation, https://pytorch-adaptive-computation-time.readthedocs.io/en/latest/
Project-URL: Repository, https://github.com/maxwells-daemons/pytorch-adaptive-computation-time
